example_pkg/__init__.py
example_pkg/test.py
chexampletest-0.0.1.dist-info/LICENSE
chexampletest-0.0.1.dist-info/METADATA
chexampletest-0.0.1.dist-info/WHEEL
chexampletest-0.0.1.dist-info/top_level.txt
chexampletest-0.0.1.dist-info/RECORD
